equiboots/EquiBootsClass.py
equiboots/StatisticalTester.py
equiboots/__init__.py
equiboots/healer.py
equiboots/logo.py
equiboots/metrics.py
equiboots/plots.py
equiboots/tables.py
equiboots-0.0.1a11.dist-info/licenses/LICENSE.md
equiboots-0.0.1a11.dist-info/METADATA
equiboots-0.0.1a11.dist-info/WHEEL
equiboots-0.0.1a11.dist-info/top_level.txt
equiboots-0.0.1a11.dist-info/RECORD
